raspaJud/__init__.py
raspaJud/tjsp.py
raspajud-0.0.4.dist-info/METADATA
raspajud-0.0.4.dist-info/WHEEL
raspajud-0.0.4.dist-info/licenses/LICENSE
raspajud-0.0.4.dist-info/RECORD
